AIWM/Predict.py
AIWM/Test_Package.py
AIWM/__init__.py
AIWM-1.0.dist-info/METADATA
AIWM-1.0.dist-info/WHEEL
AIWM-1.0.dist-info/top_level.txt
AIWM-1.0.dist-info/RECORD
